{"source":"Weather Union (Zomato) \u2014 hyperlocal ground sensors","fetched_at":"2026-07-22T22:09:42+0000","stations":[{"name":"Bengaluru \u00b7 Indiranagar","lat":12.9784,"lon":77.6408,"temperature_c":21.83,"humidity_pct":86.33,"wind_speed_ms":0.48,"wind_direction":317.9,"rain_intensity":0,"aqi_pm10":null,"aqi_pm25":null},{"name":"Bengaluru \u00b7 HSR Layout","lat":12.91,"lon":77.64,"temperature_c":21.38,"humidity_pct":83.47,"wind_speed_ms":2.54,"wind_direction":135.1,"rain_intensity":0,"aqi_pm10":null,"aqi_pm25":null},{"name":"Bengaluru \u00b7 Marathahalli","lat":12.9568,"lon":77.7011,"temperature_c":21.58,"humidity_pct":86.98,"wind_speed_ms":1.68,"wind_direction":48.2,"rain_intensity":0,"aqi_pm10":null,"aqi_pm25":null},{"name":"Bengaluru \u00b7 Bellandur","lat":12.9258,"lon":77.676,"temperature_c":21.22,"humidity_pct":83.94,"wind_speed_ms":1.22,"wind_direction":190.7,"rain_intensity":0,"aqi_pm10":null,"aqi_pm25":null},{"name":"Bengaluru \u00b7 Sarjapur","lat":12.878,"lon":77.718,"temperature_c":21.22,"humidity_pct":83.94,"wind_speed_ms":1.22,"wind_direction":190.7,"rain_intensity":0,"aqi_pm10":null,"aqi_pm25":null},{"name":"Bengaluru \u00b7 BTM Layout","lat":12.9165,"lon":77.6101,"temperature_c":21.71,"humidity_pct":84.69,"wind_speed_ms":2.63,"wind_direction":90.5,"rain_intensity":0,"aqi_pm10":null,"aqi_pm25":null},{"name":"Bengaluru \u00b7 Banashankari","lat":12.9251,"lon":77.5468,"temperature_c":21.43,"humidity_pct":84.78,"wind_speed_ms":0.32,"wind_direction":117,"rain_intensity":0,"aqi_pm10":null,"aqi_pm25":null},{"name":"Bengaluru \u00b7 Rajajinagar","lat":12.989,"lon":77.552,"temperature_c":21.6,"humidity_pct":86.17,"wind_speed_ms":0.13,"wind_direction":175.2,"rain_intensity":0,"aqi_pm10":null,"aqi_pm25":null},{"name":"Bengaluru \u00b7 Yelahanka","lat":13.1007,"lon":77.5963,"temperature_c":21.21,"humidity_pct":84.26,"wind_speed_ms":0.61,"wind_direction":192.3,"rain_intensity":0,"aqi_pm10":null,"aqi_pm25":null},{"name":"Bengaluru \u00b7 Jp Nagar","lat":12.9081,"lon":77.5853,"temperature_c":21.41,"humidity_pct":88.82,"wind_speed_ms":0.65,"wind_direction":289.8,"rain_intensity":0,"aqi_pm10":null,"aqi_pm25":null},{"name":"Bengaluru \u00b7 Indiranagar 100ft","lat":12.97,"lon":77.64,"temperature_c":21.83,"humidity_pct":86.33,"wind_speed_ms":0.48,"wind_direction":317.9,"rain_intensity":0,"aqi_pm10":null,"aqi_pm25":null},{"name":"Mumbai \u00b7 Dadar","lat":19.018,"lon":72.842,"temperature_c":26.83,"humidity_pct":93.2,"wind_speed_ms":2.54,"wind_direction":97.3,"rain_intensity":0.2,"aqi_pm10":null,"aqi_pm25":null},{"name":"Mumbai \u00b7 Goregaon","lat":19.164,"lon":72.85,"temperature_c":26.43,"humidity_pct":98.56,"wind_speed_ms":1.2,"wind_direction":337,"rain_intensity":0.2,"aqi_pm10":null,"aqi_pm25":null},{"name":"Mumbai \u00b7 Navi Mumbai","lat":19.033,"lon":73.0297,"temperature_c":26.41,"humidity_pct":96.92,"wind_speed_ms":1.56,"wind_direction":192.6,"rain_intensity":0,"aqi_pm10":null,"aqi_pm25":null},{"name":"Delhi \u00b7 Hauz Khas","lat":28.547,"lon":77.207,"temperature_c":29.23,"humidity_pct":85.41,"wind_speed_ms":0.68,"wind_direction":100.36,"rain_intensity":0,"aqi_pm10":null,"aqi_pm25":null},{"name":"Delhi \u00b7 Karol Bagh","lat":28.651,"lon":77.19,"temperature_c":29.23,"humidity_pct":78.78,"wind_speed_ms":0.92,"wind_direction":153.7,"rain_intensity":0,"aqi_pm10":null,"aqi_pm25":null},{"name":"Gurgaon \u00b7 DLF","lat":28.472,"lon":77.093,"temperature_c":28.5,"humidity_pct":79.05,"wind_speed_ms":0.32,"wind_direction":90,"rain_intensity":0,"aqi_pm10":null,"aqi_pm25":null},{"name":"Pune \u00b7 Koregaon Park","lat":18.5362,"lon":73.8939,"temperature_c":24.64,"humidity_pct":72.33,"wind_speed_ms":1.83,"wind_direction":229.5,"rain_intensity":0,"aqi_pm10":null,"aqi_pm25":null},{"name":"Pune \u00b7 Hadapsar","lat":18.502,"lon":73.929,"temperature_c":24.39,"humidity_pct":82.34,"wind_speed_ms":1.6,"wind_direction":344.3,"rain_intensity":0,"aqi_pm10":null,"aqi_pm25":null},{"name":"Pune \u00b7 Viman Nagar","lat":18.568,"lon":73.914,"temperature_c":23.81,"humidity_pct":87.58,"wind_speed_ms":1.22,"wind_direction":309.7,"rain_intensity":0,"aqi_pm10":null,"aqi_pm25":null},{"name":"Pune \u00b7 Baner","lat":18.561,"lon":73.78,"temperature_c":23.42,"humidity_pct":87.89,"wind_speed_ms":0.48,"wind_direction":120,"rain_intensity":0,"aqi_pm10":null,"aqi_pm25":null},{"name":"Pune \u00b7 Aundh","lat":18.559,"lon":73.808,"temperature_c":23.48,"humidity_pct":90.8,"wind_speed_ms":0.2,"wind_direction":182.2,"rain_intensity":0,"aqi_pm10":null,"aqi_pm25":null},{"name":"Pune \u00b7 Kharadi","lat":18.552,"lon":73.954,"temperature_c":24.68,"humidity_pct":80.47,"wind_speed_ms":3.02,"wind_direction":191.3,"rain_intensity":0,"aqi_pm10":null,"aqi_pm25":null},{"name":"Hyderabad \u00b7 Banjara Hills","lat":17.418,"lon":78.45,"temperature_c":23.45,"humidity_pct":89.55,"wind_speed_ms":0.45,"wind_direction":322.8,"rain_intensity":0,"aqi_pm10":null,"aqi_pm25":null},{"name":"Hyderabad \u00b7 Madhapur","lat":17.448,"lon":78.392,"temperature_c":23.51,"humidity_pct":90.5,"wind_speed_ms":1.56,"wind_direction":295.9,"rain_intensity":0,"aqi_pm10":null,"aqi_pm25":null},{"name":"Hyderabad \u00b7 HITEC City","lat":17.4485,"lon":78.3812,"temperature_c":23.51,"humidity_pct":90.5,"wind_speed_ms":1.56,"wind_direction":295.9,"rain_intensity":0,"aqi_pm10":null,"aqi_pm25":null},{"name":"Hyderabad \u00b7 Kukatpally","lat":17.4849,"lon":78.4138,"temperature_c":23.43,"humidity_pct":87.91,"wind_speed_ms":0.39,"wind_direction":359.6,"rain_intensity":0,"aqi_pm10":null,"aqi_pm25":null},{"name":"Hyderabad \u00b7 Secunderabad","lat":17.4399,"lon":78.4983,"temperature_c":23.76,"humidity_pct":81.66,"wind_speed_ms":0.48,"wind_direction":233.5,"rain_intensity":0,"aqi_pm10":null,"aqi_pm25":null},{"name":"Chennai \u00b7 Porur","lat":13.038,"lon":80.158,"temperature_c":29.54,"humidity_pct":79.51,"wind_speed_ms":0,"wind_direction":135.1,"rain_intensity":0,"aqi_pm10":null,"aqi_pm25":null},{"name":"Chennai \u00b7 Tambaram","lat":12.9249,"lon":80.1,"temperature_c":29.52,"humidity_pct":84.61,"wind_speed_ms":0.22,"wind_direction":314.8,"rain_intensity":0,"aqi_pm10":null,"aqi_pm25":null},{"name":"Kolkata \u00b7 Park Street","lat":22.555,"lon":88.351,"temperature_c":26.45,"humidity_pct":100,"wind_speed_ms":1.24,"wind_direction":222,"rain_intensity":0.2,"aqi_pm10":null,"aqi_pm25":null},{"name":"Kolkata \u00b7 Salt Lake","lat":22.58,"lon":88.42,"temperature_c":26.61,"humidity_pct":89.83,"wind_speed_ms":0.1,"wind_direction":345.7,"rain_intensity":0,"aqi_pm10":null,"aqi_pm25":null},{"name":"Kolkata \u00b7 Ballygunge","lat":22.531,"lon":88.365,"temperature_c":26.67,"humidity_pct":90.67,"wind_speed_ms":0.32,"wind_direction":210.7,"rain_intensity":0,"aqi_pm10":null,"aqi_pm25":null}],"probed_misses":55}